odoo/addons/budget_activity_purchase/README.rst
odoo/addons/budget_activity_purchase/__init__.py
odoo/addons/budget_activity_purchase/__manifest__.py
odoo/addons/budget_activity_purchase/models/__init__.py
odoo/addons/budget_activity_purchase/models/purchase.py
odoo/addons/budget_activity_purchase/readme/CONTRIBUTORS.md
odoo/addons/budget_activity_purchase/readme/DESCRIPTION.md
odoo/addons/budget_activity_purchase/readme/USAGE.md
odoo/addons/budget_activity_purchase/static/description/icon.png
odoo/addons/budget_activity_purchase/static/description/index.html
odoo/addons/budget_activity_purchase/tests/__init__.py
odoo/addons/budget_activity_purchase/tests/test_budget_activity_purchase.py
odoo/addons/budget_activity_purchase/views/purchase_budget_move.xml
odoo/addons/budget_activity_purchase/views/purchase_view.xml
odoo_addon_budget_activity_purchase-18.0.1.0.0.1.dist-info/METADATA
odoo_addon_budget_activity_purchase-18.0.1.0.0.1.dist-info/WHEEL
odoo_addon_budget_activity_purchase-18.0.1.0.0.1.dist-info/top_level.txt
odoo_addon_budget_activity_purchase-18.0.1.0.0.1.dist-info/RECORD
